certbot_dns_ispconfig/__init__.py
certbot_dns_ispconfig/dns_ispconfig.py
certbot_dns_ispconfig/dns_ispconfig_test.py
certbot_v4_dns_ispconfig-0.4.2.dist-info/METADATA
certbot_v4_dns_ispconfig-0.4.2.dist-info/WHEEL
certbot_v4_dns_ispconfig-0.4.2.dist-info/entry_points.txt
certbot_v4_dns_ispconfig-0.4.2.dist-info/licenses/LICENSE.txt
certbot_v4_dns_ispconfig-0.4.2.dist-info/RECORD
