Metadata-Version: 2.4
Name: certbot-v4-dns-ispconfig
Version: 0.4.2
Summary: ispconfig DNS Authenticator plugin for Certbot v5.0+
Project-URL: Homepage, https://github.com/paalcyberbook/certbot-v4-dns-ispconfig
Project-URL: Bug Reports, https://github.com/paalcyberbook/certbot-v4-dns-ispconfig/issues
Project-URL: Source, https://github.com/paalcyberbook/certbot-v4-dns-ispconfig
Project-URL: ForkedFrom, https://github.com/m42e/certbot-dns-ispconfig
Author-email: Matthias Bilger <matthias@bilger.info>, "Paal A. Bergsmark" <paal@kunnskap.no>
License:    Copyright 2015 Electronic Frontier Foundation and others
License-File: LICENSE.txt
Keywords: authenticator,certbot,dns,ispconfig,plugin
Classifier: Development Status :: 4 - Beta
Classifier: Intended Audience :: System Administrators
Classifier: License :: OSI Approved :: Apache Software License
Classifier: Operating System :: OS Independent
Classifier: Programming Language :: Python :: 3
Classifier: Programming Language :: Python :: 3.8
Classifier: Programming Language :: Python :: 3.9
Classifier: Programming Language :: Python :: 3.10
Classifier: Programming Language :: Python :: 3.11
Classifier: Programming Language :: Python :: 3.12
Classifier: Topic :: Internet :: WWW/HTTP
Classifier: Topic :: Security
Classifier: Topic :: System :: Networking
Classifier: Topic :: System :: Systems Administration
Requires-Python: >=3.8
Requires-Dist: acme>=2.11.0
Requires-Dist: certbot>=4.2.0
Requires-Dist: requests>=2.25.0
Provides-Extra: dev
Requires-Dist: mock>=4.0.0; extra == 'dev'
Requires-Dist: pytest-cov>=2.0.0; extra == 'dev'
Requires-Dist: pytest>=6.0.0; extra == 'dev'
Requires-Dist: requests-mock>=1.10.0; extra == 'dev'
